flashbots_header_signer/__init__.py
flashbots_header_signer/flashbots_signer.py
flashbots_header_signer-0.1.2.dist-info/licenses/LICENSE.txt
flashbots_header_signer-0.1.2.dist-info/METADATA
flashbots_header_signer-0.1.2.dist-info/WHEEL
flashbots_header_signer-0.1.2.dist-info/top_level.txt
flashbots_header_signer-0.1.2.dist-info/RECORD
